proca/__init__.py
proca/client.py
proca/config.py
proca/context.py
proca/friendly.py
proca/main.py
proca/query.py
proca/theme.py
proca/util.py
proca/cmd/__init__.py
proca/cmd/action.py
proca/cmd/campaign.py
proca/cmd/key.py
proca/cmd/org.py
proca/cmd/page.py
proca/cmd/server.py
proca/cmd/service.py
proca/cmd/template.py
proca/cmd/user.py
proca-0.3.9.dist-info/METADATA
proca-0.3.9.dist-info/WHEEL
proca-0.3.9.dist-info/entry_points.txt
proca-0.3.9.dist-info/top_level.txt
proca-0.3.9.dist-info/RECORD
